lamini/__init__.py
lamini/cli.py
lamini/api/classifier.py
lamini/api/embedding.py
lamini/api/lamini.py
lamini/api/lamini_config.py
lamini/api/memory_rag.py
lamini/api/model_downloader.py
lamini/api/openai_client.py
lamini/api/pipeline_client.py
lamini/api/rest_requests.py
lamini/api/streaming_completion.py
lamini/api/synchronize.py
lamini/api/train.py
lamini/api/versions.py
lamini/api/utils/batch_completions.py
lamini/api/utils/batch_embeddings.py
lamini/api/utils/completion.py
lamini/api/utils/iterators.py
lamini/api/utils/reservations.py
lamini/api/utils/shutdown.py
lamini/api/utils/sql_completion.py
lamini/api/utils/sql_token_cache.py
lamini/api/utils/supported_models.py
lamini/api/utils/upload_client.py
lamini/classify/lamini_classifier.py
lamini/error/error.py
lamini/evaluators/benchmark.py
lamini/evaluators/custom/custom_evaluator.py
lamini/evaluators/custom/earnings_call_evaluator.py
lamini/evaluators/custom/ecommerce_evaluator.py
lamini/evaluators/custom/icd_evaluator.py
lamini/evaluators/custom/datasets/earnings_calls.jsonl
lamini/evaluators/custom/datasets/icd11.jsonl
lamini/evaluators/custom/datasets/shopping.jsonl
lamini/evaluators/helm/harness_evaluator.py
lamini/evaluators/helm/mmlu_evaluator.py
lamini/evaluators/helm/truthfulqa_evaluator.py
lamini/evaluators/utils/utils.py
lamini/experiment/__init__.py
lamini/experiment/base_experiment_object.py
lamini/experiment/base_memory_experiment.py
lamini/experiment/base_memory_rag.py
lamini/experiment/base_validator.py
lamini/experiment/error_analysis_concepts.py
lamini/experiment/error_analysis_eval.py
lamini/experiment/error_analysis_sql.py
lamini/experiment/memory_rag_experiment.py
lamini/experiment/utils.py
lamini/experiment/generators/__init__.py
lamini/experiment/generators/base_generator.py
lamini/experiment/generators/base_sql_generator.py
lamini/experiment/generators/comparative_question_generator.py
lamini/experiment/generators/concept_to_sql_interpretation_generator.py
lamini-3.4.6.dist-info/licenses/LICENSE
lamini-3.4.6.dist-info/METADATA
lamini-3.4.6.dist-info/WHEEL
lamini-3.4.6.dist-info/entry_points.txt
lamini-3.4.6.dist-info/top_level.txt
lamini-3.4.6.dist-info/RECORD
