Metadata-Version: 2.4
Name: lamini
Version: 3.4.6
Summary: Build on large language models faster
Author-email: Lamini <info@lamini.ai>
Classifier: Programming Language :: Python :: 3
Classifier: License :: OSI Approved :: Apache Software License
Classifier: Operating System :: OS Independent
Requires-Python: >=3.7
License-File: LICENSE
Requires-Dist: lamini-configuration[yaml]
Requires-Dist: requests
Requires-Dist: tqdm
Requires-Dist: numpy<2.0.0
Requires-Dist: jsonlines
Requires-Dist: pandas
Requires-Dist: azure-storage-blob
Requires-Dist: scikit-learn
Requires-Dist: sqlglot
Requires-Dist: aiohttp
Requires-Dist: faiss-cpu
Requires-Dist: openai
Requires-Dist: sqlalchemy
Requires-Dist: click
Requires-Dist: prettytable
Requires-Dist: fuzzywuzzy
Requires-Dist: python-Levenshtein
Requires-Dist: rapidfuzz
Requires-Dist: jaro-winkler
Requires-Dist: umap
Requires-Dist: torch
Requires-Dist: evaluate
Provides-Extra: index
Requires-Dist: faiss-cpu; extra == "index"
Provides-Extra: classifier
Requires-Dist: scikit-learn; extra == "classifier"
Dynamic: license-file
